core/__init__.py
core/farm.py
core/game.py
core/headers.py
core/info.py
core/logging_config.py
core/task.py
core/token.py
blum_rendy-0.1.dist-info/METADATA
blum_rendy-0.1.dist-info/WHEEL
blum_rendy-0.1.dist-info/top_level.txt
blum_rendy-0.1.dist-info/RECORD
