Metadata-Version: 2.1
Name: blum-rendy
Version: 0.1
Summary: Deskripsi singkat paket
Home-page: UNKNOWN
Author: Rendy
Author-email: email@domain.com
License: UNKNOWN
Platform: UNKNOWN
